<annotation>
	<folder>800600</folder>
	<filename>IMG20221202100124.jpg</filename>
	<path>C:\Users\shawn\Desktop\Data\jag+detol+coke\NBK\800600\IMG20221202100124.jpg</path>
	<source>
		<database>Unknown</database>
	</source>
	<size>
		<width>800</width>
		<height>600</height>
		<depth>3</depth>
	</size>
	<segmented>0</segmented>
	<object>
		<name>Dettol</name>
		<pose>Unspecified</pose>
		<truncated>0</truncated>
		<difficult>0</difficult>
		<bndbox>
			<xmin>147</xmin>
			<ymin>164</ymin>
			<xmax>255</xmax>
			<ymax>305</ymax>
		</bndbox>
	</object>
	<object>
		<name>Dettol</name>
		<pose>Unspecified</pose>
		<truncated>0</truncated>
		<difficult>0</difficult>
		<bndbox>
			<xmin>295</xmin>
			<ymin>91</ymin>
			<xmax>390</xmax>
			<ymax>234</ymax>
		</bndbox>
	</object>
	<object>
		<name>Dettol</name>
		<pose>Unspecified</pose>
		<truncated>0</truncated>
		<difficult>0</difficult>
		<bndbox>
			<xmin>364</xmin>
			<ymin>248</ymin>
			<xmax>506</xmax>
			<ymax>349</ymax>
		</bndbox>
	</object>
	<object>
		<name>Dettol</name>
		<pose>Unspecified</pose>
		<truncated>0</truncated>
		<difficult>0</difficult>
		<bndbox>
			<xmin>506</xmin>
			<ymin>211</ymin>
			<xmax>665</xmax>
			<ymax>336</ymax>
		</bndbox>
	</object>
	<object>
		<name>Dettol</name>
		<pose>Unspecified</pose>
		<truncated>0</truncated>
		<difficult>0</difficult>
		<bndbox>
			<xmin>463</xmin>
			<ymin>380</ymin>
			<xmax>581</xmax>
			<ymax>472</ymax>
		</bndbox>
	</object>
</annotation>
